klogs/__init__.py
klogs/kFormatter.py
klogs/kLogger.py
klogs/test.py
klogs_util-0.2.0.dist-info/licenses/LICENSE
klogs_util-0.2.0.dist-info/METADATA
klogs_util-0.2.0.dist-info/WHEEL
klogs_util-0.2.0.dist-info/top_level.txt
klogs_util-0.2.0.dist-info/RECORD
