Metadata-Version: 2.4
Name: kLogs-util
Version: 0.2.0
Summary: Lightweight logging utility for python. Wrapper around stdlib
Author-email: "Kevin J. Mahon" <k.mahon.dev@gmail.com>
Project-URL: Repository, https://github.com/kevin-mahon/kLogs/tree/main
Keywords: log,logging
License-File: LICENSE
Requires-Dist: executing
Requires-Dist: asttokens
Dynamic: license-file
